pii_masking/__init__.py
pii_masking/masker.py
pii_masking/utils.py
piidata_masker-1.0.4.dist-info/licenses/LICENSE
piidata_masker-1.0.4.dist-info/METADATA
piidata_masker-1.0.4.dist-info/WHEEL
piidata_masker-1.0.4.dist-info/top_level.txt
piidata_masker-1.0.4.dist-info/RECORD
