Metadata-Version: 2.4
Name: piidata-masker
Version: 1.0.4
Summary: A library for masking PII (Personally Identifiable Information) in text
Home-page: https://github.com/lamebrain0/piidata-masker
Author: lamebrain0
Classifier: Development Status :: 3 - Alpha
Classifier: Intended Audience :: Developers
Classifier: License :: OSI Approved :: MIT License
Classifier: Programming Language :: Python :: 3
Classifier: Programming Language :: Python :: 3.7
Classifier: Programming Language :: Python :: 3.8
Classifier: Programming Language :: Python :: 3.9
Classifier: Programming Language :: Python :: 3.10
Requires-Python: >=3.7
License-File: LICENSE
Dynamic: home-page
Dynamic: license-file
Dynamic: requires-python
